flask_dbmigrate.py
setup.py
Flask_DBMigrate.egg-info/PKG-INFO
Flask_DBMigrate.egg-info/SOURCES.txt
Flask_DBMigrate.egg-info/dependency_links.txt
Flask_DBMigrate.egg-info/not-zip-safe
Flask_DBMigrate.egg-info/requires.txt
Flask_DBMigrate.egg-info/top_level.txt